tkinter3d/__init__.py
tkinter3d/core.py
tkinter3d/tools.py
tkinter3d-0.0.4.dist-info/licenses/LICENSE
tkinter3d-0.0.4.dist-info/METADATA
tkinter3d-0.0.4.dist-info/WHEEL
tkinter3d-0.0.4.dist-info/top_level.txt
tkinter3d-0.0.4.dist-info/RECORD
