Metadata-Version: 2.4
Name: tkinter3d
Version: 0.0.4
Summary: a tkinter extention for 3d displaying
Home-page: https://github.com/MatthewKim12/tkinter3d
Author: MatthewKim12
Author-email: kimdjn12@gmail.com
Project-URL: Source Code, https://github.com/MatthewKim12/tkinter3d/tree/main/code
Classifier: Programming Language :: Python :: 3
Classifier: License :: OSI Approved :: MIT License
Classifier: Operating System :: OS Independent
Requires-Python: >=3.10
License-File: LICENSE
Dynamic: license-file
